Metadata-Version: 2.1
Name: tasnif
Version: 0.1.11
Summary: A simple library for unsupervised image clustering
Home-page: https://github.com/cobanov/tasnif
Author: Mert Cobanov
Author-email: mertcobanov@gmail.com
License: MIT
Classifier: License :: OSI Approved :: MIT License
Classifier: Programming Language :: Python :: 3
Classifier: Programming Language :: Python :: 3.6
Classifier: Programming Language :: Python :: 3.7
Classifier: Programming Language :: Python :: 3.8
Classifier: Programming Language :: Python :: 3.9
Requires-Python: >=3.9
License-File: LICENSE
